fluffy_id/__init__.py
fluffy_id/cli.py
fluffy_id/fluffy_id.py
fluffy_id-0.2.0.dist-info/AUTHORS.rst
fluffy_id-0.2.0.dist-info/LICENSE
fluffy_id-0.2.0.dist-info/METADATA
fluffy_id-0.2.0.dist-info/WHEEL
fluffy_id-0.2.0.dist-info/entry_points.txt
fluffy_id-0.2.0.dist-info/top_level.txt
fluffy_id-0.2.0.dist-info/RECORD
