Metadata-Version: 2.1
Name: fluffy-id
Version: 0.2.0
Summary: Quickly and easily generate individual or bulk sets of globally unique identifiers (GUIDs).
Home-page: https://github.com/yoophi/fluffy-id
Author: Pyunghyuk Yoo
Author-email: yoophi@gmail.com
License: MIT license
Keywords: fluffy_id
Platform: UNKNOWN
Classifier: Development Status :: 2 - Pre-Alpha
Classifier: Intended Audience :: Developers
Classifier: License :: OSI Approved :: MIT License
Classifier: Natural Language :: English
Classifier: Programming Language :: Python :: 3
Classifier: Programming Language :: Python :: 3.5
Classifier: Programming Language :: Python :: 3.6
Classifier: Programming Language :: Python :: 3.7
Classifier: Programming Language :: Python :: 3.8
Requires-Python: >=3.5
Requires-Dist: Click (>=7.0)
